vartoml/__init__.py
vartoml-0.9.7.dist-info/LICENSE
vartoml-0.9.7.dist-info/METADATA
vartoml-0.9.7.dist-info/WHEEL
vartoml-0.9.7.dist-info/RECORD
