Metadata-Version: 2.1
Name: vartoml
Version: 0.9.7
Summary: Enable variables in a TOML file
Home-page: https://codeberg.org/ManfredLotz/vartoml
License: MIT
Author: Manfred Lotz
Author-email: manfred.lotz@posteo.de
Requires-Python: >=3.5
Classifier: License :: OSI Approved :: MIT License
Classifier: Programming Language :: Python :: 3
Classifier: Programming Language :: Python :: 3.5
Classifier: Programming Language :: Python :: 3.6
Classifier: Programming Language :: Python :: 3.7
Classifier: Programming Language :: Python :: 3.8
Classifier: Programming Language :: Python :: 3.9
Classifier: Programming Language :: Python :: 3.10
Classifier: Programming Language :: Python :: 3.11
Classifier: Programming Language :: Python :: 3.12
Requires-Dist: toml (>=0.9)
Project-URL: Repository, https://codeberg.org/ManfredLotz/vartoml
